Metadata-Version: 2.1
Name: domain-classifier
Version: 0.0.4
Summary: Use PFAM domains to classify DNA or proteins to taxonomic domain
Home-page: https://github.com/asafpr/domain_classifier
Author: Asaf Peer
Author-email: asaf.peer@jax.org
License: MIT
Platform: UNKNOWN
